README.txt
setup.py
collective/__init__.py
collective.pathtouid.egg-info/PKG-INFO
collective.pathtouid.egg-info/SOURCES.txt
collective.pathtouid.egg-info/dependency_links.txt
collective.pathtouid.egg-info/entry_points.txt
collective.pathtouid.egg-info/namespace_packages.txt
collective.pathtouid.egg-info/not-zip-safe
collective.pathtouid.egg-info/paster_plugins.txt
collective.pathtouid.egg-info/requires.txt
collective.pathtouid.egg-info/top_level.txt
collective/pathtouid/__init__.py
collective/pathtouid/browser.pt
collective/pathtouid/browser.py
collective/pathtouid/browser.txt
collective/pathtouid/configure.zcml
collective/pathtouid/interfaces.py
collective/pathtouid/tests.py
collective/pathtouid/utility.py
docs/HISTORY.txt
docs/INSTALL.txt
docs/LICENSE.GPL
docs/LICENSE.txt