Metadata-Version: 1.0
Name: collective.pathtouid
Version: 0.1.0a
Summary: Plone utility to change relative or absolute path inside text to UID (and resolveuid)
Home-page: http://svn.plone.org/svn/collective/collective.pathtouid
Author: RedTurtle Technology
Author-email: sviluppoplone@redturtle.net
License: GPL
Keywords: plone c3p uid path url
Platform: UNKNOWN
Classifier: Framework :: Plone
Classifier: Programming Language :: Python
Classifier: Development Status :: 3 - Alpha
